hnvclient/__init__.py
hnvclient/client.py
hnvclient/common/__init__.py
hnvclient/common/constant.py
hnvclient/common/exception.py
hnvclient/common/model.py
hnvclient/common/utils.py
hnvclient/tests/__init__.py
hnvclient/tests/test_client.py
hnvclient/tests/utils.py
hnvclient/tests/common/__init__.py
hnvclient/tests/common/test_model.py
hnvclient/tests/common/test_utils.py
hnvclient/tests/fake/__init__.py
hnvclient/tests/fake/fake_response.py
hnvclient/tests/fake/response/__init__.py
hnvclient/tests/fake/response/acl.json
hnvclient/tests/fake/response/acl_rules.json
hnvclient/tests/fake/response/backend_address_pools.json
hnvclient/tests/fake/response/bgp_peers.json
hnvclient/tests/fake/response/bgp_routers.json
hnvclient/tests/fake/response/frontend_ip_configurations.json
hnvclient/tests/fake/response/inbound_nat_rules.json
hnvclient/tests/fake/response/ip_configurations.json
hnvclient/tests/fake/response/ip_pools.json
hnvclient/tests/fake/response/load_balancer_manager.json
hnvclient/tests/fake/response/load_balancer_mux.json
hnvclient/tests/fake/response/load_balancers.json
hnvclient/tests/fake/response/load_balancing_rules.json
hnvclient/tests/fake/response/logical_networks.json
hnvclient/tests/fake/response/logical_subnets.json
hnvclient/tests/fake/response/network_connections.json
hnvclient/tests/fake/response/network_interfaces.json
hnvclient/tests/fake/response/outbound_nat_rules.json
hnvclient/tests/fake/response/probes.json
hnvclient/tests/fake/response/public_ip_addresses.json
hnvclient/tests/fake/response/route_tables.json
hnvclient/tests/fake/response/routes.json
hnvclient/tests/fake/response/virtual_networks.json
hnvclient/tests/fake/response/virtual_subnetworks.json
hnvclient/tests/fake/response/virtual_switch_manager.json
python_hnvclient-0.1.0.dist-info/DESCRIPTION.rst
python_hnvclient-0.1.0.dist-info/METADATA
python_hnvclient-0.1.0.dist-info/RECORD
python_hnvclient-0.1.0.dist-info/WHEEL
python_hnvclient-0.1.0.dist-info/metadata.json
python_hnvclient-0.1.0.dist-info/pbr.json
python_hnvclient-0.1.0.dist-info/top_level.txt
