Metadata-Version: 2.0
Name: python-hnvclient
Version: 0.1.0
Summary: Python client for the HNV (Hyper-V Network Virtualization) REST API.
Home-page: https://github.com/cloudbase/python-hnvclient
Author: Cloudbase Solutions Srl
Author-email: acoman@cloudbasesolutions.com
License: UNKNOWN
Platform: UNKNOWN
Classifier: Environment :: OpenStack
Classifier: Intended Audience :: Information Technology
Classifier: Intended Audience :: System Administrators
Classifier: License :: OSI Approved :: Apache Software License
Classifier: Operating System :: OS Independent
Classifier: Programming Language :: Python
Classifier: Programming Language :: Python :: 2
Classifier: Programming Language :: Python :: 2.7
Classifier: Programming Language :: Python :: 3
Classifier: Programming Language :: Python :: 3.3
Classifier: Programming Language :: Python :: 3.4
Requires-Dist: oslo.i18n (>=2.1.0)
Requires-Dist: oslo.log (>=3.11.0)
Requires-Dist: pbr (>=1.8)
Requires-Dist: requests
Requires-Dist: requests-ntlm
Requires-Dist: six (>=1.7.0)
